fluidityai/__init__.py
fluidityai/fluidity_classes.py
fluidityai/fluidity_examples.py
fluidityai/fluidity_globals.py
fluidityai/fluidity_tests.py
fluidityai/ord.py
fluidityai/pwd.py
fluidityai/taxi.py
at_20250801-0.1.0.dist-info/LICENSE
at_20250801-0.1.0.dist-info/METADATA
at_20250801-0.1.0.dist-info/WHEEL
at_20250801-0.1.0.dist-info/top_level.txt
at_20250801-0.1.0.dist-info/RECORD
