Metadata-Version: 2.1
Name: at-20250801
Version: 0.1.0
Summary: Classes for AI workflow development
Home-page: https://github.com/AshT-Python/Fluidity
Author: Ash Thakur
Author-email: ash.thakur@yahoo.co.uk
Classifier: Programming Language :: Python :: 3
Classifier: License :: OSI Approved :: MIT License
Classifier: Operating System :: OS Independent
Requires-Python: >=3.6
License-File: LICENSE
Requires-Dist: detoxify==0.5.2
Requires-Dist: llm-guard==0.3.14
Requires-Dist: openai==1.97.1
Requires-Dist: pandas==1.5.3
Requires-Dist: PyPDF2==3.0.1
Requires-Dist: scikit-learn==1.7.1
Requires-Dist: sentence-transformers==4.1.0
Requires-Dist: duckdb==1.2.2
